LICENSE
MANIFEST.in
README.rst
setup.py
leocornus/__init__.py
leocornus.recipe.ci.egg-info/PKG-INFO
leocornus.recipe.ci.egg-info/SOURCES.txt
leocornus.recipe.ci.egg-info/dependency_links.txt
leocornus.recipe.ci.egg-info/entry_points.txt
leocornus.recipe.ci.egg-info/namespace_packages.txt
leocornus.recipe.ci.egg-info/not-zip-safe
leocornus.recipe.ci.egg-info/requires.txt
leocornus.recipe.ci.egg-info/top_level.txt
leocornus/recipe/__init__.py
leocornus/recipe/ci/README.rst
leocornus/recipe/ci/__init__.py
leocornus/recipe/ci/utils.py
leocornus/recipe/ci/tests/__init__.py
leocornus/recipe/ci/tests/testDoctests.py