Metadata-Version: 1.1
Name: leocornus.recipe.ci
Version: 0.0.1
Summary: zc.buildout recipe for manage and execute CI test cases.
Home-page: http://github.com/leocornus/leocornus.recipe.ci
Author: Sean Chen
Author-email: sean.chen@leocorn.com
License: GPLv2
Keywords: development buildout recipe package ci
Platform: UNKNOWN
Classifier: Framework :: Buildout
Classifier: Intended Audience :: Developers
Classifier: License :: OSI Approved :: GNU General Public License (GPL)
Classifier: Topic :: Software Development :: Build Tools
Classifier: Topic :: Software Development :: Libraries :: Python Modules
